sgframework-0.2.3.dist-info/DESCRIPTION.rst
sgframework-0.2.3.dist-info/RECORD
sgframework-0.2.3.dist-info/METADATA
sgframework-0.2.3.dist-info/WHEEL
sgframework-0.2.3.dist-info/top_level.txt
sgframework-0.2.3.dist-info/metadata.json
sgframework/exceptions.py
sgframework/constants.py
sgframework/framework.py
sgframework/version.py
sgframework/__init__.py
sgframework-0.2.3.data/scripts/servicemanager
sgframework-0.2.3.data/scripts/canadapterlib.py
sgframework-0.2.3.data/scripts/canadapter
