Metadata-Version: 2.0
Name: sgframework
Version: 0.2.3
Summary: A framework for the Secure Gateway concept architecture.
Home-page: https://github.com/caran/SecureGateway
Author: Jonas Berg
Author-email: caranopensource@semcon.com
License: BSD
Keywords: sgframework
Platform: UNKNOWN
Classifier: Development Status :: 3 - Alpha
Classifier: Intended Audience :: Developers
Classifier: License :: OSI Approved :: BSD License
Classifier: Natural Language :: English
Classifier: Operating System :: POSIX :: Linux
Classifier: Programming Language :: Python :: 3 :: Only
Classifier: Programming Language :: Python :: 3.3
Classifier: Programming Language :: Python :: 3.4
Classifier: Programming Language :: Python :: 3.5
Classifier: Topic :: Scientific/Engineering
Classifier: Topic :: Software Development :: Embedded Systems
Classifier: Topic :: Software Development :: Libraries
Classifier: Topic :: System :: Hardware :: Hardware Drivers
Requires-Dist: can4python
Requires-Dist: paho-mqtt
